AUTHORS.txt
COPYING.txt
MANIFEST.in
Makefile
README.md
make.bat
setup.py
doc/Makefile
doc/audio.rst
doc/conf.py
doc/copying.rst
doc/index.rst
doc/install.rst
doc/integration.rst
doc/loaders.rst
doc/make.bat
doc/news.rst
doc/openal.rst
doc/python.inv
doc/todos.rst
doc/images/coordinate_rhs.dia
doc/images/coordinate_rhs.png
doc/images/copprocessing.dia
doc/images/listener_default.png
doc/images/listener_xyz.png
doc/images/listener_xz.png
doc/images/openalaudio.dia
doc/images/openalaudio.png
doc/images/openallistener.dia
examples/audioplayer.py
examples/hey.ogg
examples/hey.wav
examples/player.py
examples/3D_Audio/OpenAL32.dll
examples/3D_Audio/OpenAL_3D.py
examples/3D_Audio/tone5.wav
examples/EFX/LQ_Snare Rev.wav
examples/EFX/OpenAL32.dll
examples/EFX/OpenAL_EFX.py
examples/HRTF/OpenAL32.dll
examples/HRTF/OpenAL_HRTF.py
examples/HRTF/default-44100.mhr
examples/HRTF/default-48000.mhr
examples/HRTF/tone5.wav
examples/HRTF/HRTF_Tables/1002_hrtf_33100.mhr
examples/HRTF/HRTF_Tables/1003_hrtf_44100.mhr
examples/HRTF/HRTF_Tables/1004_hrtf_44100.mhr
examples/HRTF/HRTF_Tables/1005_hrtf_44100.mhr
examples/HRTF/HRTF_Tables/1006_hrtf_44100.mhr
examples/HRTF/HRTF_Tables/1007_hrtf_44100.mhr
examples/HRTF/HRTF_Tables/1008_hrtf_44100.mhr
examples/HRTF/HRTF_Tables/1009_hrtf_44100.mhr
examples/HRTF/HRTF_Tables/1012_hrtf_44100.mhr
examples/HRTF/HRTF_Tables/1013_hrtf_44100.mhr
examples/HRTF/HRTF_Tables/1014_hrtf_44100.mhr
examples/HRTF/HRTF_Tables/1015_hrtf_44100.mhr
examples/HRTF/HRTF_Tables/1016_hrtf_44100.mhr
examples/HRTF/HRTF_Tables/1017_hrtf_44100.mhr
examples/HRTF/HRTF_Tables/1018_hrtf_44100.mhr
examples/HRTF/HRTF_Tables/1020_hrtf_44100.mhr
examples/HRTF/HRTF_Tables/1021_hrtf_44100.mhr
examples/HRTF/HRTF_Tables/1022_hrtf_44100.mhr
examples/HRTF/HRTF_Tables/1023_hrtf_44100.mhr
examples/HRTF/HRTF_Tables/1025_hrtf_44100.mhr
examples/HRTF/HRTF_Tables/1026_hrtf_44100.mhr
examples/HRTF/HRTF_Tables/1028_hrtf_44100.mhr
examples/HRTF/HRTF_Tables/1029_hrtf_44100.mhr
python_openal.egg-info/PKG-INFO
python_openal.egg-info/SOURCES.txt
python_openal.egg-info/dependency_links.txt
python_openal.egg-info/top_level.txt