Metadata-Version: 2.1
Name: python-openal
Version: 0.4.1
Summary: Python OpenAL bindings
Home-page: https://github.com/JessicaTegner/PyAL
Author: Marcus von Appen
Author-email: marcus@sysfault.org
License: Public Domain / zlib
Classifier: Development Status :: 4 - Beta
Classifier: Intended Audience :: Developers
Classifier: License :: Public Domain
Classifier: License :: OSI Approved :: zlib/libpng License
Classifier: Operating System :: OS Independent
Classifier: Programming Language :: Python
Classifier: Programming Language :: Python :: 2.7
Classifier: Programming Language :: Python :: 3
Classifier: Programming Language :: Python :: 3.2
Classifier: Programming Language :: Python :: 3.3
Classifier: Programming Language :: Python :: Implementation :: CPython
Classifier: Programming Language :: Python :: Implementation :: IronPython
Classifier: Programming Language :: Python :: Implementation :: PyPy
Classifier: Topic :: Multimedia :: Sound/Audio
Classifier: Topic :: Software Development :: Libraries :: Python Modules
License-File: COPYING.txt
License-File: AUTHORS.txt
